pypolisen/Client.py
pypolisen/__init__.py
pypolisen/tests/__init__.py
pypolisen/tests/test_get_items.py
pypolisen/tests/test_get_suggestions.py
pypolisen-1.0.dist-info/METADATA
pypolisen-1.0.dist-info/RECORD
pypolisen-1.0.dist-info/WHEEL
pypolisen-1.0.dist-info/entry_points.txt
pypolisen-1.0.dist-info/top_level.txt
